nebula/__init__.py
nebula/client.py
nebula/exceptions.py
nebula/models.py
nebula/utils.py
thirdweb_nebula-0.1.0.dist-info/METADATA
thirdweb_nebula-0.1.0.dist-info/WHEEL
thirdweb_nebula-0.1.0.dist-info/RECORD
