Metadata-Version: 2.1
Name: thirdweb-nebula
Version: 0.1.0
Summary: A Python SDK for interacting with the Nebula API
Home-page: https://github.com/gwszeto/nebula-python
License: MIT
Keywords: nebula,thirdweb,api,sdk,blockchain
Author: Stanley
Author-email: gw.stanley.szeto@gmail.com
Requires-Python: >=3.12,<4.0
Classifier: Development Status :: 4 - Beta
Classifier: Intended Audience :: Developers
Classifier: License :: OSI Approved :: MIT License
Classifier: Operating System :: OS Independent
Classifier: Programming Language :: Python :: 3
Classifier: Programming Language :: Python :: 3.12
Classifier: Topic :: Internet :: WWW/HTTP
Classifier: Topic :: Software Development :: Libraries :: Python Modules
Requires-Dist: pydantic (>=2.10.4,<3.0.0)
Requires-Dist: requests (>=2.31.0,<3.0.0)
Requires-Dist: sseclient (>=0.0.27,<0.0.28)
Project-URL: Documentation, https://github.com/gwszeto/nebula-python#readme
Project-URL: Repository, https://github.com/gwszeto/nebula-python
